RumboVeta/RumboVeta.py
RumboVeta/__init__.py
RumboVeta1-1.1.dist-info/METADATA
RumboVeta1-1.1.dist-info/WHEEL
RumboVeta1-1.1.dist-info/license
RumboVeta1-1.1.dist-info/top_level.txt
RumboVeta1-1.1.dist-info/RECORD
