Metadata-Version: 2.1
Name: RumboVeta1
Version: 1.1
Summary: Con esta Biblioteca Calculas el rumbo de veta
Author: Julio Gomez
Requires-Python: >=3.12.1
License-File: license
